fastapi_jsend-0.1.1.dist-info/licenses/LICENSE.txt
jsend/__init__.py
jsend/exceptions.py
jsend/models.py
jsend/utils.py
fastapi_jsend-0.1.1.dist-info/METADATA
fastapi_jsend-0.1.1.dist-info/WHEEL
fastapi_jsend-0.1.1.dist-info/top_level.txt
fastapi_jsend-0.1.1.dist-info/RECORD
